odoo/addons/website_menu_by_user_status/README.rst
odoo/addons/website_menu_by_user_status/__init__.py
odoo/addons/website_menu_by_user_status/__manifest__.py
odoo/addons/website_menu_by_user_status/models/__init__.py
odoo/addons/website_menu_by_user_status/models/website_menu.py
odoo/addons/website_menu_by_user_status/static/description/icon.png
odoo/addons/website_menu_by_user_status/tests/__init__.py
odoo/addons/website_menu_by_user_status/tests/test_website_menu.py
odoo/addons/website_menu_by_user_status/views/website_menu.xml
odoo11_addon_website_menu_by_user_status-11.0.1.0.0.dist-info/DESCRIPTION.rst
odoo11_addon_website_menu_by_user_status-11.0.1.0.0.dist-info/METADATA
odoo11_addon_website_menu_by_user_status-11.0.1.0.0.dist-info/RECORD
odoo11_addon_website_menu_by_user_status-11.0.1.0.0.dist-info/WHEEL
odoo11_addon_website_menu_by_user_status-11.0.1.0.0.dist-info/metadata.json
odoo11_addon_website_menu_by_user_status-11.0.1.0.0.dist-info/top_level.txt
